neurozip/__init__.py
neurozip/api.py
neurozip/dataloaders/__init__.py
neurozip/dataloaders/utils.py
neurozip/preprocess/__init__.py
neurozip/preprocess/optical.py
neurozip/types/__init__.py
neurozip/types/nzloader.py
neurozip/types/nzpipeline.py
neurozip/types/nzpreprocessor.py
neurozip-0.1.1.dist-info/licenses/LICENSE
neurozip-0.1.1.dist-info/METADATA
neurozip-0.1.1.dist-info/WHEEL
neurozip-0.1.1.dist-info/top_level.txt
neurozip-0.1.1.dist-info/RECORD
